{
  "fabric:load_conditions": [
    {
      "condition": "fabric:all_mods_loaded",
      "values": [
        "tfc"
      ]
    }
  ],
  "type": "create:sequenced_assembly",
  "conditions": [
    {
      "type": "forge:mod_loaded",
      "modid": "tfc"
    }
  ],
  "ingredient": {
    "item": "tfc:wood/planks/sycamore_slab"
  },
  "loops": 1,
  "results": [
    {
      "item": "railways:track_tfc_sycamore"
    }
  ],
  "sequence": [
    {
      "type": "create:deploying",
      "ingredients": [
        {
          "item": "railways:track_incomplete_tfc_sycamore"
        },
        [
          {
            "tag": "forge:rods/wrought_iron"
          },
          {
            "tag": "forge:rods/zinc"
          }
        ]
      ],
      "results": [
        {
          "item": "railways:track_incomplete_tfc_sycamore"
        }
      ]
    },
    {
      "type": "create:deploying",
      "ingredients": [
        {
          "item": "railways:track_incomplete_tfc_sycamore"
        },
        [
          {
            "tag": "forge:rods/wrought_iron"
          },
          {
            "tag": "forge:rods/zinc"
          }
        ]
      ],
      "results": [
        {
          "item": "railways:track_incomplete_tfc_sycamore"
        }
      ]
    },
    {
      "type": "create:pressing",
      "ingredients": [
        {
          "item": "railways:track_incomplete_tfc_sycamore"
        }
      ],
      "results": [
        {
          "item": "railways:track_incomplete_tfc_sycamore"
        }
      ]
    }
  ],
  "transitionalItem": {
    "item": "railways:track_incomplete_tfc_sycamore"
  }
}