{
	"credit": "Made with Blockbench",
	"textures": {
		"1": "railways:block/track_switch/brass_casing_xxshort",
		"particle": "create:block/brass_casing"
	},
	"elements": [
		{
			"name": "crossbar",
			"from": [5.5, 12, 7],
			"to": [10.5, 13, 9],
			"rotation": {"angle": 0, "axis": "y", "origin": [0, -4, 0]},
			"faces": {
				"north": {"uv": [0, 0, 6, 1], "texture": "#1"},
				"east": {"uv": [0, 0, 2, 1], "texture": "#1"},
				"south": {"uv": [0, 0, 5, 1], "texture": "#1"},
				"west": {"uv": [0, 0, 2, 1], "texture": "#1"},
				"up": {"uv": [0, 0, 5, 2], "texture": "#1"},
				"down": {"uv": [0, 0, 5, 2], "texture": "#1"}
			}
		},
		{
			"name": "top",
			"from": [2.25, 17, 6.8],
			"to": [13.75, 18.5, 9.2],
			"rotation": {"angle": 0, "axis": "y", "origin": [0, -4, 0]},
			"faces": {
				"north": {"uv": [2, 0, 13.5, 1.5], "texture": "#1"},
				"east": {"uv": [0, 1, 2, 2.5], "texture": "#1"},
				"south": {"uv": [2, 0, 13.5, 1.5], "texture": "#1"},
				"west": {"uv": [0, 1, 2, 2.5], "texture": "#1"},
				"up": {"uv": [2, 0, 13.5, 2], "texture": "#1"},
				"down": {"uv": [2, 0, 13.5, 2], "texture": "#1"}
			}
		},
		{
			"name": "side",
			"from": [7, 5.5, 6.9],
			"to": [8.5, 18.3, 9.05],
			"rotation": {"angle": -22.5, "axis": "z", "origin": [8, 4.5, 8]},
			"faces": {
				"north": {"uv": [2, 0, 14.8, 1.5], "rotation": 270, "texture": "#1"},
				"east": {"uv": [2, 0, 14.8, 2], "rotation": 90, "texture": "#1"},
				"south": {"uv": [2, 0, 14.8, 1.5], "rotation": 90, "texture": "#1"},
				"west": {"uv": [2, 0, 14.8, 2], "rotation": 90, "texture": "#1"},
				"up": {"uv": [0, 0, 2, 1], "rotation": 90, "texture": "#1"},
				"down": {"uv": [0, 1, 2, 2], "rotation": 90, "texture": "#1"}
			}
		},
		{
			"name": "side",
			"from": [7.5, 5.5, 6.9],
			"to": [9, 18.3, 9.1],
			"rotation": {"angle": 22.5, "axis": "z", "origin": [8, 4.5, 8]},
			"faces": {
				"north": {"uv": [1, 0, 13.8, 1.5], "rotation": 270, "texture": "#1"},
				"east": {"uv": [1, 0, 13.8, 2], "rotation": 90, "texture": "#1"},
				"south": {"uv": [1, 0, 13.8, 1.5], "rotation": 90, "texture": "#1"},
				"west": {"uv": [1, 0, 13.8, 2], "rotation": 90, "texture": "#1"},
				"up": {"uv": [0, 0, 2, 1], "rotation": 90, "texture": "#1"},
				"down": {"uv": [0, 0, 2, 1], "rotation": 90, "texture": "#1"}
			}
		}
	],
	"display": {
		"thirdperson_righthand": {
			"rotation": [75, 45, 0],
			"translation": [0, 2, 0],
			"scale": [0.375, 0.375, 0.375]
		},
		"thirdperson_lefthand": {
			"rotation": [75, -135, 0],
			"translation": [0, 2, 0],
			"scale": [0.375, 0.375, 0.375]
		},
		"firstperson_righthand": {
			"rotation": [0, 135, 0],
			"scale": [0.4, 0.4, 0.4]
		},
		"firstperson_lefthand": {
			"rotation": [0, -45, 0],
			"scale": [0.4, 0.4, 0.4]
		},
		"ground": {
			"translation": [0, 3, 0],
			"scale": [0.25, 0.25, 0.25]
		},
		"gui": {
			"rotation": [30, 45, 0],
			"translation": [0.5, -0.5, 0],
			"scale": [0.5, 0.5, 0.5]
		},
		"head": {
			"rotation": [0, 180, 0],
			"translation": [0.5, 9.5, 1],
			"scale": [0.375, 0.375, 0.375]
		},
		"fixed": {
			"translation": [0, -0.5, 0],
			"scale": [0.6, 0.6, 0.6]
		}
	},
	"groups": [
		{
			"name": "flag",
			"origin": [8, 8.5, 8],
			"color": 0,
			"children": [0, 1, 2, 3]
		}
	]
}